ErisPulse_OpenAI/Core.py
ErisPulse_OpenAI/__init__.py
erispulse_openai-2.1.3.dist-info/licenses/LICENSE
erispulse_openai-2.1.3.dist-info/METADATA
erispulse_openai-2.1.3.dist-info/WHEEL
erispulse_openai-2.1.3.dist-info/entry_points.txt
erispulse_openai-2.1.3.dist-info/top_level.txt
erispulse_openai-2.1.3.dist-info/RECORD
