Metadata-Version: 2.4
Name: ErisPulse-OpenAI
Version: 2.1.3
Summary: ErisPulse OpenAI 通用接口封装模块
Author-email: wsu2059q <wsu2059@qq.com>
License: MIT License
Project-URL: homepage, https://github.com/ErisPulse/ErisPulse-OpenAI
Requires-Python: >=3.9
License-File: LICENSE
Requires-Dist: openai
Dynamic: license-file
